{
    "train_loss": [
        NaN,
        NaN,
        NaN
    ],
    "train_accuracy": [
        0.2706666588783264,
        0.24975000321865082,
        0.24975000321865082
    ],
    "train_macro_precision": [
        0.5822526453455109,
        0.0624375,
        0.0624375
    ],
    "train_macro_recall": [
        0.2709112264202654,
        0.25,
        0.25
    ],
    "train_macro_f1": [
        0.14700426669937325,
        0.0999199839967194,
        0.0999199839967194
    ],
    "train_micro_f1": [
        0.2706666666661667,
        0.2497499999995,
        0.2497499999995
    ],
    "train_weighted_f1": [
        0.14690720009379576,
        0.09982006401272268,
        0.09982006401272268
    ],
    "train_confidence": [
        NaN,
        NaN,
        NaN
    ],
    "val_loss": [
        NaN,
        NaN,
        NaN
    ],
    "val_accuracy": [
        0.25224998593330383,
        0.25224998593330383,
        0.25224998593330383
    ],
    "val_macro_precision": [
        0.0630625,
        0.0630625,
        0.0630625
    ],
    "val_macro_recall": [
        0.24999999999999992,
        0.24999999999999992,
        0.24999999999999992
    ],
    "val_macro_f1": [
        0.10071870632852804,
        0.10071870632852804,
        0.10071870632852804
    ],
    "val_micro_f1": [
        0.2522499999995,
        0.2522499999995,
        0.2522499999995
    ],
    "val_weighted_f1": [
        0.10162517468548479,
        0.10162517468548479,
        0.10162517468548479
    ],
    "val_confidence": [
        NaN,
        NaN,
        NaN
    ],
    "test_loss": [
        NaN,
        NaN,
        NaN
    ],
    "test_accuracy": [
        0.25,
        0.25,
        0.25
    ],
    "test_macro_precision": [
        0.06249999999999999,
        0.06249999999999999,
        0.06249999999999999
    ],
    "test_macro_recall": [
        0.2499999999999999,
        0.2499999999999999,
        0.2499999999999999
    ],
    "test_macro_f1": [
        0.09999999999991997,
        0.09999999999991997,
        0.09999999999991997
    ],
    "test_micro_f1": [
        0.24999999999949996,
        0.24999999999949996,
        0.24999999999949996
    ],
    "test_weighted_f1": [
        0.09999999999991997,
        0.09999999999991997,
        0.09999999999991997
    ],
    "test_confidence": [
        NaN,
        NaN,
        NaN
    ],
    "grad_norm": [
        NaN,
        NaN,
        NaN
    ],
    "fractional_applied_params": [
        203.0,
        203.0,
        203.0
    ],
    "epoch_time": [
        644.0109305381775,
        635.0964665412903,
        633.4914057254791
    ],
    "throughput_samples_per_sec": [
        167.69901701784497,
        170.05290643193726,
        170.48376508962673
    ],
    "lr": [
        2e-05,
        2e-05,
        2e-05
    ]
}