{
    "train_loss": [
        1.0336078569000842,
        NaN,
        NaN,
        NaN,
        NaN
    ],
    "train_accuracy": [
        0.7369791865348816,
        0.0,
        0.0,
        0.0,
        0.0
    ],
    "train_macro_precision": [
        0.7600447310704218,
        0.0,
        0.0,
        0.0,
        0.0
    ],
    "train_macro_recall": [
        0.7350707933815918,
        0.0,
        0.0,
        0.0,
        0.0
    ],
    "train_macro_f1": [
        0.73968601127104,
        0.0,
        0.0,
        0.0,
        0.0
    ],
    "train_micro_f1": [
        0.7369791666661665,
        0.0,
        0.0,
        0.0,
        0.0
    ],
    "train_weighted_f1": [
        0.7394545175569385,
        0.0,
        0.0,
        0.0,
        0.0
    ],
    "train_confidence": [
        0.3932558393069342,
        NaN,
        NaN,
        NaN,
        NaN
    ],
    "val_loss": [
        0.0,
        0.0,
        0.0,
        0.0,
        0.0
    ],
    "val_accuracy": [
        0.24791666865348816,
        0.24791666865348816,
        0.24791666865348816,
        0.24791666865348816,
        0.24791666865348816
    ],
    "val_macro_precision": [
        0.061979166666666655,
        0.061979166666666655,
        0.061979166666666655,
        0.061979166666666655,
        0.061979166666666655
    ],
    "val_macro_recall": [
        0.24999999999999992,
        0.24999999999999992,
        0.24999999999999992,
        0.24999999999999992,
        0.24999999999999992
    ],
    "val_macro_f1": [
        0.09933222036719917,
        0.09933222036719917,
        0.09933222036719917,
        0.09933222036719917,
        0.09933222036719917
    ],
    "val_micro_f1": [
        0.24791666666616663,
        0.24791666666616663,
        0.24791666666616663,
        0.24791666666616663,
        0.24791666666616663
    ],
    "val_weighted_f1": [
        0.09850445186413918,
        0.09850445186413918,
        0.09850445186413918,
        0.09850445186413918,
        0.09850445186413918
    ],
    "val_confidence": [
        NaN,
        NaN,
        NaN,
        NaN,
        NaN
    ],
    "test_loss": [
        0.0,
        0.0,
        0.0,
        0.0,
        0.0
    ],
    "test_accuracy": [
        0.25,
        0.25,
        0.25,
        0.25,
        0.25
    ],
    "test_macro_precision": [
        0.06249999999999999,
        0.06249999999999999,
        0.06249999999999999,
        0.06249999999999999,
        0.06249999999999999
    ],
    "test_macro_recall": [
        0.2499999999999999,
        0.2499999999999999,
        0.2499999999999999,
        0.2499999999999999,
        0.2499999999999999
    ],
    "test_macro_f1": [
        0.09999999999991997,
        0.09999999999991997,
        0.09999999999991997,
        0.09999999999991997,
        0.09999999999991997
    ],
    "test_micro_f1": [
        0.24999999999949996,
        0.24999999999949996,
        0.24999999999949996,
        0.24999999999949996,
        0.24999999999949996
    ],
    "test_weighted_f1": [
        0.09999999999991997,
        0.09999999999991997,
        0.09999999999991997,
        0.09999999999991997,
        0.09999999999991997
    ],
    "test_confidence": [
        NaN,
        NaN,
        NaN,
        NaN,
        NaN
    ],
    "grad_norm": [
        0.7489450040216857,
        0.0,
        0.0,
        0.0,
        0.0
    ],
    "nonfinite_grad_tensors": [
        0.00980392156862745,
        0.0,
        0.0,
        0.0,
        0.0
    ],
    "nonfinite_train_loss_batches": [
        3171,
        3375,
        3375,
        3375,
        3375
    ],
    "nonfinite_val_loss_batches": [
        375,
        375,
        375,
        375,
        375
    ],
    "nonfinite_test_loss_batches": [
        238,
        238,
        238,
        238,
        238
    ],
    "fractional_applied_params": [
        23.0,
        0.0,
        0.0,
        0.0,
        0.0
    ],
    "epoch_time": [
        123.60694670677185,
        59.224416971206665,
        61.71365690231323,
        62.87280225753784,
        62.46434688568115
    ],
    "throughput_samples_per_sec": [
        52.81256574912518,
        0.0,
        0.0,
        0.0,
        0.0
    ],
    "lr": [
        2e-05,
        2e-05,
        2e-05,
        2e-05,
        2e-05
    ]
}